graphpipe/__init__.py
graphpipe/convert.py
graphpipe/remote.py
graphpipe/graphpipefb/Error.py
graphpipe/graphpipefb/IOMetadata.py
graphpipe/graphpipefb/InferRequest.py
graphpipe/graphpipefb/InferResponse.py
graphpipe/graphpipefb/MetadataRequest.py
graphpipe/graphpipefb/MetadataResponse.py
graphpipe/graphpipefb/Req.py
graphpipe/graphpipefb/Request.py
graphpipe/graphpipefb/Tensor.py
graphpipe/graphpipefb/Type.py
graphpipe/graphpipefb/__init__.py
graphpipe-1.0.4.dist-info/METADATA
graphpipe-1.0.4.dist-info/RECORD
graphpipe-1.0.4.dist-info/WHEEL
graphpipe-1.0.4.dist-info/top_level.txt
