Metadata-Version: 2.1
Name: graphpipe
Version: 1.0.4
Summary: Graphpipe client and helpers
Home-page: https://oracle.github.io/graphpipe
Author: OCI ML Team
Author-email: vish.ishaya@oracle.com
License: UNKNOWN
Platform: UNKNOWN
Requires-Dist: numpy (>=1.13.3)
Requires-Dist: requests (==2.18.4)
Requires-Dist: flatbuffers (==1.9.0)
